subset/DICTIONARY_LICENSE
subset/LICENSE
subset/__init__.py
subset/app.py
subset/dictionary.txt
subset-0.1.2.dist-info/LICENSE
subset-0.1.2.dist-info/METADATA
subset-0.1.2.dist-info/WHEEL
subset-0.1.2.dist-info/entry_points.txt
subset-0.1.2.dist-info/top_level.txt
subset-0.1.2.dist-info/RECORD
