Metadata-Version: 2.1
Name: subset
Version: 0.1.2
Summary: A cli-based word game
Home-page: https://github.com/rightbrace/subset-game.git
Author: Josef Duchesne
Author-email: josefduchesne@outlook.com
License: MIT
Platform: UNKNOWN
Classifier: Programming Language :: Python :: 3
Classifier: License :: OSI Approved :: MIT License
Classifier: Operating System :: OS Independent
Requires-Python: >=3.5
Requires-Dist: colorama
